lasso/__init__.py
lasso/logging.py
lasso/diffcrash/__init__.py
lasso/diffcrash/diffcrash_run.py
lasso/diffcrash/run.py
lasso/dimred/__init__.py
lasso/dimred/dimred_run.py
lasso/dimred/graph_laplacian.py
lasso/dimred/hashing.py
lasso/dimred/hashing_sphere.py
lasso/dimred/run.py
lasso/dimred/sphere/__init__.py
lasso/dimred/sphere/algorithms.py
lasso/dimred/svd/__init__.py
lasso/dimred/svd/clustering_betas.py
lasso/dimred/svd/html_str_eles.py
lasso/dimred/svd/keyword_types.py
lasso/dimred/svd/plot_beta_clusters.py
lasso/dimred/svd/pod_functions.py
lasso/dimred/svd/subsampling_methods.py
lasso/dyna/__init__.py
lasso/dyna/array_type.py
lasso/dyna/binout.py
lasso/dyna/d3plot.py
lasso/dyna/d3plot_header.py
lasso/dyna/femzip_mapper.py
lasso/dyna/filter_type.py
lasso/dyna/lsda_py3.py
lasso/femzip/__init__.py
lasso/femzip/femzip_api.py
lasso/femzip/fz_config.py
lasso/io/__init__.py
lasso/io/binary_buffer.py
lasso/io/files.py
lasso/math/__init__.py
lasso/math/sampling.py
lasso/math/stochastic.py
lasso/plotting/__init__.py
lasso/plotting/plot_shell_mesh.py
lasso/plotting/resources/__init__.py
lasso/utils/__init__.py
lasso/utils/console_coloring.py
lasso/utils/decorators.py
lasso/utils/language.py
lasso/utils/rich_progress_bars.py
lasso_python-2.0.4.dist-info/licenses/LICENSE.md
lasso_python-2.0.4.dist-info/METADATA
lasso_python-2.0.4.dist-info/WHEEL
lasso_python-2.0.4.dist-info/entry_points.txt
lasso_python-2.0.4.dist-info/top_level.txt
lasso_python-2.0.4.dist-info/RECORD
