Metadata-Version: 2.4
Name: lasso-python
Version: 2.0.4
Summary: An open-source CAE and Machine Learning library.
Author-email: open-lasso-python <open.lasso.python@gmail.com>
Classifier: Development Status :: 5 - Production/Stable
Classifier: Topic :: Scientific/Engineering
Classifier: Intended Audience :: Science/Research
Classifier: Topic :: Utilities
Classifier: Operating System :: Microsoft :: Windows
Classifier: Operating System :: POSIX :: Linux
Classifier: Programming Language :: Python :: 3
Classifier: Programming Language :: Python :: 3.11
Classifier: Programming Language :: Python :: 3.12
Requires-Python: >=3.11
License-File: LICENSE.md
Requires-Dist: h5py==3.*
Requires-Dist: scipy==1.*
Requires-Dist: numpy>2.2
Requires-Dist: plotly==5.*
Requires-Dist: psutil==5.*
Requires-Dist: rich==13.*
Requires-Dist: pandas==2.*
Requires-Dist: scikit_learn==1.*
Dynamic: license-file
